{"version":"1.0","title":"phlox-corporate-pro-businsess-db5b165","type":"section","content":[{"id":"db5b165","elType":"section","settings":{"layout":"full_width","gap":"no","content_position":"middle","structure":"20","padding":{"unit":"px","top":"220","right":"35","bottom":"200","left":"35","isLinked":false},"custom_css":"selector{\n    background: transparent linear-gradient(180deg, var(--e-global-color-primary) 0%, var(--e-global-color-secondary) 50%,#ffffff 50%, #ffffff 100%);\n}","margin":{"unit":"%","top":"-3","right":0,"bottom":"0","left":0,"isLinked":false},"padding_tablet":{"unit":"px","top":"100","right":"35","bottom":"200","left":"35","isLinked":false},"reverse_order_tablet":"reverse-tablet","reverse_order_mobile":"reverse-mobile","padding_mobile":{"unit":"px","top":"80","right":"35","bottom":"50","left":"35","isLinked":false}},"elements":[{"id":"d836dd4","elType":"column","settings":{"_column_size":50,"_inline_size":75,"aux_position_type":"relative","aux_position_left":{"unit":"px","size":0,"sizes":[]},"_inline_size_tablet":100,"content_position_mobile":"center","align_mobile":"center","margin_tablet":{"unit":"%","top":"0","right":"0","bottom":"0","left":"0","isLinked":false},"padding_tablet":{"unit":"px","top":"0","right":"0","bottom":"0","left":"0","isLinked":false},"margin":{"unit":"px","top":"0","right":"0","bottom":"0","left":"0","isLinked":false},"custom_css":"@media screen and (max-width:800px){\n    selector{\n        margin-top:-9%;\n    }\n}"},"elements":[{"id":"7c05e1f","elType":"widget","settings":{"deeplink":"","carousel_navigation_control":"","carousel_navigation_control_text_next":"Next","carousel_navigation_control_text_prev":"Prev","button_style":"pattern-2","carousel_autoplay":"","space":35,"image_aspect_ratio":"custom","image_aspect_ratio_custom":0.93000000000000004884981308350688777863979339599609375,"img_border_radius":{"unit":"px","top":"20","right":"20","bottom":"0","left":"0","isLinked":false},"title_typography_typography":"custom","title_typography_font_size":{"unit":"px","size":27,"sizes":[]},"title_typography_font_weight":"bold","info_typography_typography":"custom","info_typography_font_family":"Open Sans","info_typography_font_size":{"unit":"px","size":16,"sizes":[]},"info_typography_font_weight":"400","info_typography_font_style":"normal","info_spacing_between":{"unit":"px","size":5,"sizes":[]},"_margin":{"unit":"%","top":"0","right":"2","bottom":"0","left":"-17","isLinked":false},"custom_css":"selector .entry-main{\n    box-shadow: 0px 6px 35px\n        #0000001A;\n    background:\n        #fff;\n    margin-top: -27px;\n    border-radius: 0 0 20px 20px;\n    padding: 20px 0px 1px 70px;\n}\nselector .entry-title:before{\n    content: '';\n    width: 34px;\n    height: 4px;\n    background: transparent linear-gradient(90deg, var(--e-global-color-8e4d53e) 0%, var(--e-global-color-1d2832ff) 100%) 0% 0% no-repeat padding-box;\n    box-shadow: 0px 10px 30px #2E3CFF73;\n    border-radius: 20px;\n    position: absolute;\n    left: -45px;\n    top: 45%;\n    margin-right: 10px !important;\n}\nselector .aux-carousel-controls{\n    display: none;\n}\n\/*-----hover-----*\/\nselector article:hover .entry-main{\n    background: transparent linear-gradient(256deg, #000000 0%, #343434 100%);\n}\nselector article:hover .entry-title a,selector article:hover .entry-tax a{\n    color: #fff !important;\n}\n\/*-----Responsive-----*\/\n@media screen and (max-width:1440px){\n    selector .entry-title a{\n        font-size:20px !important;\n    }\n    selector .entry-main{\n        padding: 15px 0px 10px 40px !important;\n    }\n    selector .entry-title:before{\n        width:27px !important;\n        left:-33px;\n    }\n}\n@media screen and (max-width:992px){\n    selector{\n        margin:0 15% 0 15% !important;\n    }\n}","columns_tablet":"2","num":"","_margin_mobile":{"unit":"px","top":"0","right":"0","bottom":"0","left":"0","isLinked":false},"aux_max_width_mobile":{"unit":"%","size":70,"sizes":[]},"_css_classes":"aux-car","offset":8,"_margin_tablet":{"unit":"%","top":"0","right":"0","bottom":"0","left":"0","isLinked":false},"aux_animation_name":"aux-fade-in-left","aux_animation_easing":"0.25,0.46,0.45,0.94","__dynamic__":[],"__globals__":{"title_color":"globals\/colors?id=5211b6c","title_hover_color":"globals\/colors?id=43771d5","info_color":"globals\/colors?id=5211b6c","info_hover_color":"globals\/colors?id=43771d5"}},"elements":[],"widgetType":"aux_recent_portfolios_grid_carousel"},{"id":"5cbb9f7","elType":"widget","settings":{"label":"View All Portfolio","link":{"url":"#","is_external":"","nofollow":"","custom_attributes":""},"btn_align":"center","icon_display":"yes","icon":{"value":"auxicon2 auxicon2-arrows-chevron-thin-right","library":"auxicon2"},"text_normal_typo_typography":"custom","text_normal_typo_font_size":{"unit":"px","size":18,"sizes":[]},"text_normal_typo_font_weight":"600","text_normal_typo_text_transform":"uppercase","text_hover_typo_typography":"custom","text_hover_typo_text_decoration":"underline","icon_align":"right","icon_normal_size":{"unit":"px","size":30,"sizes":[]},"_margin":{"unit":"px","top":"80","right":"0","bottom":"0","left":"450","isLinked":false},"_margin_tablet":{"unit":"px","top":"50","right":"0","bottom":"0","left":"0","isLinked":false},"custom_css":"selector .aux-overlay::before , selector .aux-overlay::after{\n    background-color: transparent !important;\n}\n@media screen and (max-width:1110px) and (min-width:1024px){\n    selector{\n        margin:80px 0 0 250px;\n    }\n}\n@media screen and (max-width:1024px) and (min-width:800px){\n    selector{\n        margin:80px 0 0 0px;\n    }\n}","__dynamic__":[],"__globals__":{"text_normal_color":"globals\/colors?id=5211b6c","icon_normal_color":"globals\/colors?id=5211b6c"}},"elements":[],"widgetType":"aux_modern_button"}],"isInner":false},{"id":"ede676e","elType":"column","settings":{"_column_size":50,"_inline_size":25,"align":"flex-end","aux_position_type":"absolute","aux_position_right":{"unit":"px","size":0,"sizes":[]},"aux_position_top":{"unit":"px","size":0,"sizes":[]},"_inline_size_tablet":100,"content_position_tablet":"center","align_tablet":"center","margin_tablet":{"unit":"%","top":"0","right":"0","bottom":"0","left":"0","isLinked":false},"aux_position_type_tablet":"relative","aux_position_top_tablet":{"unit":"%","size":-5,"sizes":[]},"margin":{"unit":"px","top":"0","right":"0","bottom":"0","left":"50","isLinked":false}},"elements":[{"id":"dfa897b","elType":"widget","settings":{"title":"","divider":"","title_secondary_before":"PORT","title_secondary_highlight":"FOLIO","title_typography_typography":"custom","title_typography_font_family":"Open Sans","title_typography_font_size":{"unit":"px","size":24,"sizes":[]},"title_typography_font_weight":"600","title_typography_letter_spacing":{"unit":"px","size":4.79999999999999982236431605997495353221893310546875,"sizes":[]},"title2_typography_typography":"custom","title2_typography_font_family":"Open Sans","title2_typography_font_size":{"unit":"px","size":22,"sizes":[]},"title2_typography_font_weight":"600","title2_typography_text_transform":"uppercase","title2_typography_letter_spacing":{"unit":"px","size":4.79999999999999982236431605997495353221893310546875,"sizes":[]},"title2_highlighted_typography_typography":"custom","title2_highlighted_typography_font_family":"Open Sans","title2_highlighted_typography_font_size":{"unit":"px","size":22,"sizes":[]},"title2_highlighted_typography_font_weight":"600","title2_highlighted_typography_text_transform":"uppercase","custom_css":"selector .aux-modern-heading-secondary{\n    box-shadow: 0px 10px 30px #2E3CFF73;\n}","title2_typography_font_size_mobile":{"unit":"px","size":18,"sizes":[]},"title2_highlighted_typography_font_size_mobile":{"unit":"px","size":18,"sizes":[]},"alignment":"left","alignment_mobile":"center","_margin":{"unit":"%","top":"","right":"","bottom":"","left":"","isLinked":true},"alignment_tablet":"center","title2_background_background":"gradient","title2_background_gradient_angle":{"unit":"deg","size":88,"sizes":[]},"title2_padding":{"unit":"px","top":"0","right":"0","bottom":"0","left":"20","isLinked":false},"title2_border_radius":{"unit":"px","top":"10","right":"0","bottom":"0","left":"10","isLinked":false},"title2_width":{"unit":"px","size":92,"sizes":[]},"title2_highlighted_background_background":"gradient","_margin_tablet":{"unit":"%","top":"0","right":"0","bottom":"0","left":"-15","isLinked":false},"title2_padding_mobile":{"unit":"px","top":"0","right":"0","bottom":"0","left":"30","isLinked":false},"title2_highlighted_margin":{"unit":"px","top":"0","right":"0","bottom":"0","left":"-3","isLinked":false},"wrapper_margin":{"unit":"px","top":"-15","right":"0","bottom":"0","left":"0","isLinked":false},"_margin_mobile":{"unit":"%","top":"0","right":"0","bottom":"0","left":"-20","isLinked":false},"aux_animation_name":"aux-fade-in-right","aux_animation_easing":"0.165,0.84,0.44,1","__dynamic__":[],"__globals__":{"title2_color":"globals\/colors?id=5211b6c","title2_background_color":"globals\/colors?id=8e4d53e","title2_background_color_b":"globals\/colors?id=1d2832ff","title2_highlighted_color":"globals\/colors?id=43771d5"}},"elements":[],"widgetType":"aux_modern_heading"},{"id":"7b66566","elType":"widget","settings":{"title":"Experienced in gallery","title_typography_typography":"custom","title_typography_font_size":{"unit":"px","size":50,"sizes":[]},"title_typography_font_weight":"600","title_typography_letter_spacing":{"unit":"px","size":-0.65000000000000002220446049250313080847263336181640625,"sizes":[]},"title_width":{"unit":"px","size":365,"sizes":[]},"divider_weight":{"unit":"px","size":5,"sizes":[]},"divider_width":{"unit":"px","size":95,"sizes":[]},"divider_color":"#CCCCCC","title_typography_text_transform":"capitalize","title_margin":{"unit":"px","top":"0","right":"0","bottom":"0","left":"0","isLinked":false},"divider_margin":{"unit":"px","top":"15","right":"0","bottom":"35","left":"0","isLinked":false},"description_typography_font_weight":"400","description_typography_line_height":{"unit":"em","size":1.399999999999999911182158029987476766109466552734375,"sizes":[]},"title_typography_font_size_tablet":{"unit":"px","size":33,"sizes":[]},"title_typography_font_size_mobile":{"unit":"px","size":26,"sizes":[]},"description_typography_font_family":"Open Sans","description_typography_font_size":{"unit":"px","size":16,"sizes":[]},"description_typography_font_size_tablet":{"unit":"px","size":14,"sizes":[]},"description_typography_font_size_mobile":{"unit":"px","size":14,"sizes":[]},"description_typography_text_transform":"capitalize","custom_css":"@media screen and (max-width:1366px) and (min-width:1024px){\n    selector .aux-modern-heading-primary{\n        font-size:40px;\n    }\n}","divider":"","divider_margin_mobile":{"unit":"em","top":"1","right":"0","bottom":"2","left":"6","isLinked":false},"title_width_tablet":{"unit":"px","size":607,"sizes":[]},"aux_animation_name":"aux-fade-in-up","aux_animation_easing":"0.165,0.84,0.44,1","__dynamic__":[],"alignment_tablet":"center","__globals__":{"title_color":"globals\/colors?id=43771d5"}},"elements":[],"widgetType":"aux_modern_heading"},{"id":"3d650ae","elType":"widget","settings":{"nav_type":"custom","prev_icon":{"value":"auxicon auxicon-arrow","library":"auxicon"},"next_icon":{"value":"auxicon auxicon-arrow","library":"auxicon"},"nav_target":".aux-car","navigation_align":"flex-start","navigation_align_tablet":"center","navigation_gap":{"unit":"px","size":30,"sizes":[]},"icon_bg_background":"classic","icon_box_shadow_box_shadow_type":"yes","icon_box_shadow_box_shadow":{"horizontal":0,"vertical":0,"blur":25,"spread":0,"color":"rgba(0, 0, 0, 0.1607843137254902)"},"icon_border_radius":{"unit":"px","top":"50","right":"50","bottom":"50","left":"50","isLinked":true},"icon_padding":{"unit":"px","top":"17","right":"18","bottom":"17","left":"18","isLinked":false},"icon_hover_bg_background":"gradient","icon_hover_box_shadow_box_shadow_type":"yes","icon_hover_color":"#FFFFFF","_margin":{"unit":"px","top":"80","right":"0","bottom":"0","left":"0","isLinked":false},"custom_css":"selector .aux-prev span{\n    transform: rotate(180deg);\n}\n@media screen and (max-width:992px){\n    selector .aux-next{\n        position: absolute;\n        top: 345px;\n        right: 0;\n        z-index: 99;\n    }\n    selector .aux-prev{\n        position: absolute;\n        top: 345px;\n        left: 0;\n        z-index: 99;\n    }\n}\n@media screen and (max-width:480px){\n    selector .aux-next{\n        right: -20px;\n        top: 210px;\n    }\n    selector .aux-prev{\n        left: -20px;\n        top: 210px;\n    }\n}","icon_size":{"unit":"px","size":18,"sizes":[]},"icon_hover_size":{"unit":"px","size":18,"sizes":[]},"_margin_mobile":{"unit":"px","top":"0","right":"0","bottom":"0","left":"0","isLinked":false},"__dynamic__":[],"__globals__":{"icon_bg_color":"globals\/colors?id=43771d5","icon_color":"globals\/colors?id=5211b6c","icon_hover_bg_color":"globals\/colors?id=primary","icon_hover_bg_color_b":"globals\/colors?id=secondary"}},"elements":[],"widgetType":"aux_carousel_navigation"}],"isInner":false}],"isInner":false}]}